exif_database/__init__.py
exif_database/__main__.py
exif_database/exiftool.py
exif_database-0.1.1.dist-info/LICENSE.txt
exif_database-0.1.1.dist-info/METADATA
exif_database-0.1.1.dist-info/WHEEL
exif_database-0.1.1.dist-info/top_level.txt
exif_database-0.1.1.dist-info/RECORD
