Metadata-Version: 2.2
Name: exif-database
Version: 0.1.1
Summary: Dump pictures metadata into a MongoDB database for statistics purposes
Author-email: Aloïs Micard <alois@micard.lu>
Project-URL: Homepage, https://git.creekorful.cloud/creekorful/exif-database
Project-URL: Issues, https://git.creekorful.cloud/creekorful/exif-database/issues
Project-URL: Changelog, https://git.creekorful.cloud/creekorful/exif-database/src/branch/main/Changelog.md
Classifier: Programming Language :: Python :: 3
Classifier: Operating System :: OS Independent
Requires-Python: >=3.8
License-File: LICENSE.txt
Requires-Dist: pymongo>=4.10
Requires-Dist: platformdirs>=4.3
